drang_run/__init__.py
drang_run/simpleeval.py
drang_run-0.4.4.dist-info/entry_points.txt
drang_run-0.4.4.dist-info/LICENSE
drang_run-0.4.4.dist-info/WHEEL
drang_run-0.4.4.dist-info/METADATA
drang_run-0.4.4.dist-info/RECORD
