Metadata-Version: 2.1
Name: drang-run
Version: 0.4.4
Summary: Generate a run of integers or characters. Similar to jot and seq.
Home-page: http://github.com/jneug/drang-run
License: MIT
Author: J. Neugebauer
Author-email: github@neugebauer.cc
Requires-Python: >=3.6.2,<4.0.0
Classifier: License :: OSI Approved :: MIT License
Classifier: Programming Language :: Python :: 3
Classifier: Programming Language :: Python :: 3.10
Classifier: Programming Language :: Python :: 3.7
Classifier: Programming Language :: Python :: 3.8
Classifier: Programming Language :: Python :: 3.9
Requires-Dist: click (>=8.0.3,<9.0.0)
Project-URL: Repository, http://github.com/jneug/drang-run
